COPYING
MANIFEST.in
README.md
setup.py
ansible_playbook_debugger.egg-info/PKG-INFO
ansible_playbook_debugger.egg-info/SOURCES.txt
ansible_playbook_debugger.egg-info/dependency_links.txt
ansible_playbook_debugger.egg-info/not-zip-safe
ansible_playbook_debugger.egg-info/requires.txt
ansible_playbook_debugger.egg-info/top_level.txt
bin/ansible-playbook-debugger
lib/ansibledebugger/__init__.py
lib/ansibledebugger/action_plugin_wrapper.py
lib/ansibledebugger/runner_wrapper.py
lib/ansibledebugger/interpreter/__init__.py
lib/ansibledebugger/interpreter/simple_interpreter.py
lib/ansibledebugger/utils/__init__.py
tests/action_plugin_wrapper_test.py
tests/interpreter_test.py
tests/runner_wrapper_test.py
tests/utils_test.py
tests/testutils/__init__.py