Metadata-Version: 1.1
Name: ansible-playbook-debugger
Version: 0.2.2
Summary: Debugger for Ansible Playbook
Home-page: https://github.com/ks888/ansible-playbook-debugger
Author: Kishin Yagami
Author-email: k.yagami.suou@gmail.com
License: GPLv3
Platform: UNKNOWN
Classifier: Environment :: Console
Classifier: Intended Audience :: Developers
Classifier: Intended Audience :: System Administrators
Classifier: License :: OSI Approved :: GNU General Public License v3 (GPLv3)
Classifier: Programming Language :: Python
Classifier: Topic :: Software Development
Classifier: Topic :: Software Development :: Debuggers
Classifier: Topic :: System :: Systems Administration
